<properties>
    <attributes name="applogokey" value="0=icon.png"/>
    <attributes name="DELETE_PACKAGES" value="false"/>
    <attributes name="UPDATE_DEVICE_STATS" value="false"/>
    <attributes name="ACCESS_NETWORK_STATE" value="true"/>
    <attributes name="ACCESS_WIFI_STATE" value="false"/>
    <attributes name="SET_WALLPAPER_HINTS" value="false"/>
    <attributes name="mwaddrkey" value="10.10.4.106"/>
    <attributes name="win8packagenamekey" value="HelloWorld"/>
    <attributes name="portkey" value=""/>
    <attributes name="INTERNAL_SYSTEM_WINDOW" value="false"/>
    <attributes name="wp8cycle4key" value=""/>
    <attributes name="WRITE_SETTINGS" value="false"/>
    <attributes name="ID_CAP_WALLET_SECUREELEMENT" value="true"/>
    <attributes name="startupformkey" value="frmHome"/>
    <attributes name="ACCOUNT_MANAGER" value="false"/>
    <attributes name="tcpalm480basefontsize" value="14"/>
    <attributes name="wp8cycle6key" value=""/>
    <attributes name="wp8packagepublisheridkey" value=""/>
    <attributes name="Home_or_Work_Networking" value="true"/>
    <attributes name="andminsdkkey" value="2.1"/>
    <attributes name="PERSISTENT_ACTIVITY" value="false"/>
    <attributes name="Internet(Client_AND_Server)" value="true"/>
    <attributes name="READ_SMS" value="false"/>
    <attributes name="ID_CAP_ISV_CAMERA" value="true"/>
    <attributes name="applepushfunc" value="None"/>
    <attributes name="Internet(Client)" value="true"/>
    <attributes name="urlschemanameorder" value=""/>
    <attributes name="win8packagelogokey" value=""/>
    <attributes name="desktopwebwidthoption" value="Percentage"/>
    <attributes name="MODIFY_AUDIO_SETTINGS" value="false"/>
    <attributes name="CAMERA" value="false"/>
    <attributes name="tcnth480basefontsize" value="17"/>
    <attributes name="GLOBAL_SEARCH" value="false"/>
    <attributes name="hybridaddrkey" value=""/>
    <attributes name="winsmoothscrollkey" value="true"/>
    <attributes name="CLEAR_APP_USER_DATA" value="false"/>
    <attributes name="passwordkey" value="kds/0eUc+i3BqFqSkpCk4g=="/>
    <attributes name="tcnth440basefontsize" value="15"/>
    <attributes name="wp8flipsmallkey" value=""/>
    <attributes name="ACCESS_COARSE_LOCATION" value="false"/>
    <attributes name="RESTART_PACKAGES" value="false"/>
    <attributes name="win8widelogokey" value=""/>
    <attributes name="ID_CAP_PHONEDIALER" value="true"/>
    <attributes name="backward_compatibility_mode" value="false"/>
    <attributes name="appversionkey" value="1.0.0"/>
    <attributes name="removeprintstatements" value="true"/>
    <attributes name="mwcontextkey" value=""/>
    <attributes name="apploadeventkey" value="None"/>
    <attributes name="CALL_PHONE" value="false"/>
    <attributes name="INSTALL_PACKAGES" value="false"/>
    <attributes name="BIND_WALLPAPER" value="false"/>
    <attributes name="isNewAppWithRespectToAndroidPackageName" value="true"/>
    <attributes name="ID_CAP_MEDIALIB_AUDIO" value="true"/>
    <attributes name="tcbb320basefontsize" value="15"/>
    <attributes name="SET_ANIMATION_SCALE" value="false"/>
    <attributes name="AUTHENTICATE_ACCOUNTS" value="false"/>
    <attributes name="wp8cycle1key" value=""/>
    <attributes name="ID_CAP_LOCATION" value="true"/>
    <attributes name="ID_CAP_WALLET" value="true"/>
    <attributes name="desktopwebtitle" value=""/>
    <attributes name="wp8tilestitlekey" value=""/>
    <attributes name="WRITE_SECURE_SETTINGS" value="false"/>
    <attributes name="androidloadindicatorkey" value="true"/>
    <attributes name="ID_CAP_PROXIMITY" value="true"/>
    <attributes name="SET_TIME" value="false"/>
    <attributes name="Enterprise_Authentication" value="true"/>
    <attributes name="ID_CAP_REMOVABLE_STORAGE" value="true"/>
    <attributes name="DIAGNOSTIC" value="false"/>
    <attributes name="WRITE_CALENDAR" value="false"/>
    <attributes name="Videos_Library_Access" value="true"/>
    <attributes name="wp8cycle2key" value=""/>
    <attributes name="WRITE_SMS" value="false"/>
    <attributes name="ID_REQ_GYROSCOPE" value="false"/>
    <attributes name="DEVICE_POWER" value="false"/>
    <attributes name="win8versionminorkey" value="0"/>
    <attributes name="androidscreenextralarge" value="true"/>
    <attributes name="RECORD_AUDIO" value="false"/>
    <attributes name="SUBSCRIBED_FEEDS_WRITE" value="false"/>
    <attributes name="bbusemds" value="false"/>
    <attributes name="ipadportraitmodekey" value="true"/>
    <attributes name="appnamekey" value="HelloWorld"/>
    <attributes name="iphonebundleversionkey" value="1.0"/>
    <attributes name="wp8packageauthorkey" value=""/>
    <attributes name="READ_HISTORY_BOOKMARKS" value="false"/>
    <attributes name="androidmapkey" value=""/>
    <attributes name="andtargetsdkkey" value="2.1"/>
    <attributes name="deeplinkkey" value="None"/>
    <attributes name="READ_LOGS" value="false"/>
    <attributes name="enablesearchbar" value="false"/>
    <attributes name="wp8descriptionkey" value="Sample Test Application"/>
    <attributes name="WRITE_GSERVICES" value="false"/>
    <attributes name="wp8packageversionkey" value=""/>
    <attributes name="BROADCAST_STICKY" value="false"/>
    <attributes name="CHANGE_CONFIGURATION" value="false"/>
    <attributes name="GET_ACCOUNTS" value="false"/>
    <attributes name="SET_PROCESS_LIMIT" value="false"/>
    <attributes name="MOUNT_FORMAT_FILESYSTEMS" value="false"/>
    <attributes name="PROCESS_OUTGOING_CALLS" value="false"/>
    <attributes name="BROADCAST_PACKAGE_REMOVED" value="false"/>
    <attributes name="Server side mobile web" value="false"/>
    <attributes name="wp8cycle3key" value=""/>
    <attributes name="ID_CAP_MEDIALIB_PLAYBACK" value="true"/>
    <attributes name="BLUETOOTH" value="false"/>
    <attributes name="useridkey" value=""/>
    <attributes name="mangoapptitlekey" value=",,,,,,"/>
    <attributes name="genericexceptionalert" value="false"/>
    <attributes name="win8certificatefilekey" value=""/>
    <attributes name="wp8flipmediumkey" value=""/>
    <attributes name="desktopwebwidthval" value="100"/>
    <attributes name="BIND_INPUT_METHOD" value="false"/>
    <attributes name="thinwebcontextkey" value=""/>
    <attributes name="DUMP" value="false"/>
    <attributes name="wp8tilestemplatekey" value="FLIP_TILE"/>
    <attributes name="SET_ORIENTATION" value="false"/>
    <attributes name="DISABLE_KEYGUARD" value="false"/>
    <attributes name="ID_REQ_FRONTCAMERA" value="false"/>
    <attributes name="pasteboardtype" value="systemlevel"/>
    <attributes name="tcandroid400basefontsize" value="14"/>
    <attributes name="win8packagedisplaynamekey" value="HelloWorld"/>
    <attributes name="androidscreenresizeable" value="false"/>
    <attributes name="tcandroid440basefontsize" value="15"/>
    <attributes name="MANAGE_ACCOUNTS" value="false"/>
    <attributes name="androidscreenanydensity" value="true"/>
    <attributes name="CHANGE_NETWORK_STATE" value="false"/>
    <attributes name="desktopwebaligenmentoption" value="left"/>
    <attributes name="win8badgelogokey" value=""/>
    <attributes name="hostkey" value=""/>
    <attributes name="mwportkey" value="80"/>
    <attributes name="wp8packagepublisherkey" value="Kony"/>
    <attributes name="win8certificatekey" value=""/>
    <attributes name="enablefocushtml5iphonbb" value="false"/>
    <attributes name="BRICK" value="false"/>
    <attributes name="win8packagepublichernamekey" value="Kony"/>
    <attributes name="andmaxsdkkey" value="None"/>
    <attributes name="ID_CAP_APPOINTMENTS" value="true"/>
    <attributes name="READ_SYNC_SETTINGS" value="false"/>
    <attributes name="ID_CAP_MEDIALIB_PHOTO" value="true"/>
    <attributes name="SET_PREFERRED_APPLICATIONS" value="false"/>
    <attributes name="WRITE_HISTORY_BOOKMARKS" value="false"/>
    <attributes name="INTERNET" value="true"/>
    <attributes name="GET_TASKS" value="false"/>
    <attributes name="Music_Library" value="true"/>
    <attributes name="tciphonebasefontsize" value="12"/>
    <attributes name="tabletstartupformkey" value="frmHome"/>
    <attributes name="pathpatternkey" value=""/>
    <attributes name="splashlogokey" value="0=,1=splash.png,8=splash.png,2=splash.png,3=splash.png,20=splash.png,9=splash.png,15=splash.png,14=splash.png,42=splash.png,16=splash.png,18=splash.png,43=,31=splash.png,32=splash.png,22=splash.png,23=splash.png,24=splash.png,35=splash.png,36=splash.png,21=splash.png,37=splash.png"/>
    <attributes name="USE_SIP" value="false"/>
    <attributes name="wp8iconicsmallkey" value=""/>
    <attributes name="enablepushnotifications" value="false"/>
    <attributes name="secondarytilefunctionkey" value="None"/>
    <attributes name="ACCESS_FINE_LOCATION" value="false"/>
    <attributes name="Shared_User_Certificates" value="true"/>
    <attributes name="inputaccessoryviewtype" value="nextprevtoolbar"/>
    <attributes name="imagewhendownloading" value=""/>
    <attributes name="READ_INPUT_STATE" value="false"/>
    <attributes name="INSTALL_LOCATION_PROVIDER" value="false"/>
    <attributes name="fbxfolderpathkey" value=""/>
    <attributes name="ID_RESOLUTION_HD720P" value="true"/>
    <attributes name="READ_CONTACTS" value="false"/>
    <attributes name="windowsmapkey" value=""/>
    <attributes name="ID_CAP_MICROPHONE" value="true"/>
    <attributes name="ID_CAP_VOIP" value="true"/>
    <attributes name="wintileforegroundnamekey" value="Light"/>
    <attributes name="REBOOT" value="false"/>
    <attributes name="SET_TIME_ZONE" value="false"/>
    <attributes name="ID_CAP_GAMERSERVICES" value="true"/>
    <attributes name="iphoneipadglossyeffectkey" value="false"/>
    <attributes name="tcbjs480basefontsize" value="10"/>
    <attributes name="Text_Messaging" value="true"/>
    <attributes name="HARDWARE_TEST" value="false"/>
    <attributes name="ID_RESOLUTION_WVGA" value="true"/>
    <attributes name="USE_CREDENTIALS" value="false"/>
    <attributes name="CLEAR_APP_CACHE" value="false"/>
    <attributes name="tcbjs320basefontsize" value="10"/>
    <attributes name="desktopwebbasefontsize" value="16"/>
    <attributes name="appiniteventkey" value="None"/>
    <attributes name="ID_RESOLUTION_WXGA" value="true"/>
    <attributes name="GET_PACKAGE_SIZE" value="false"/>
    <attributes name="CHANGE_WIFI_STATE" value="false"/>
    <attributes name="allowselfsignedcertificate" value="false"/>
    <attributes name="NFC" value="false"/>
    <attributes name="ID_CAP_MEDIALIB" value="true"/>
    <attributes name="tcnth240basefontsize" value="12"/>
    <attributes name="tcbb480basefontsize" value="17"/>
    <attributes name="tcandroid640basefontsize" value="19"/>
    <attributes name="desktopwebnoscriptmessage" value="To use this site, first enable your browser&#039;s JavaScript support and then refresh this page."/>
    <attributes name="tcbb360basefontsize" value="13"/>
    <attributes name="winmangotiletitlekey" value="HelloWorld"/>
    <attributes name="bgcolorkey" value="181,217,245"/>
    <attributes name="BIND_APPWIDGET" value="false"/>
    <attributes name="READ_CALENDAR" value="false"/>
    <attributes name="hybridhttpsportkey" value=""/>
    <attributes name="wp8cycle5key" value=""/>
    <attributes name="Removable_Storage" value="true"/>
    <attributes name="hybdridcontextkey" value=""/>
    <attributes name="ipadlandscapemodekey" value="true"/>
    <attributes name="KILL_BACKGROUND_PROCESSES" value="false"/>
    <attributes name="tcnth400basefontsize" value="14"/>
    <attributes name="schemekey" value=""/>
    <attributes name="androidInstallLocnPref" value="false"/>
    <attributes name="win8versionmajorkey" value="1"/>
    <attributes name="win8lockscreennotificationskey" value="not set"/>
    <attributes name="tcpalm240basefontsize" value="10"/>
    <attributes name="CHANGE_WIFI_MULTICAST_STATE" value="false"/>
    <attributes name="andapplicationtags" value=""/>
    <attributes name="exceptionalert" value="true"/>
    <attributes name="CALL_PRIVILEGED" value="false"/>
    <attributes name="wp8cycle8key" value=""/>
    <attributes name="SUBSCRIBED_FEEDS_READ" value="false"/>
    <attributes name="xhtmlfavicokey" value=""/>
    <attributes name="ID_CAP_IDENTITY_USER" value="true"/>
    <attributes name="spaipadbasefontsize" value="17"/>
    <attributes name="antialiaseddrawing" value="false"/>
    <attributes name="BLUETOOTH_ADMIN" value="false"/>
    <attributes name="READ_PHONE_STATE" value="true"/>
    <attributes name="sessionmanager" value="Kony Session Manager"/>
    <attributes name="FLASHLIGHT" value="false"/>
    <attributes name="READ_FRAME_BUFFER" value="false"/>
    <attributes name="RECEIVE_WAP_PUSH" value="false"/>
    <attributes name="wp8fliplargekey" value=""/>
    <attributes name="bbbuildoption" value="true"/>
    <attributes name="BIND_DEVICE_ADMIN" value="false"/>
    <attributes name="build" value="release"/>
    <attributes name="MANAGE_APP_TOKENS" value="false"/>
    <attributes name="winbuildoption" value="true"/>
    <attributes name="MODIFY_PHONE_STATE" value="false"/>
    <attributes name="Pictures_Library_Access" value="true"/>
    <attributes name="ID_CAP_WALLET_PAYMENTINSTRUMENTS" value="true"/>
    <attributes name="tcpalm320basefontsize" value="12"/>
    <attributes name="RECEIVE_BOOT_COMPLETED" value="false"/>
    <attributes name="androidInstallLocation" value="Auto"/>
    <attributes name="androidscreenlarge" value="true"/>
    <attributes name="tcnth360basefontsize" value="13"/>
    <attributes name="INJECT_EVENTS" value="false"/>
    <attributes name="wintilebackcolornamekey" value="128,128,128"/>
    <attributes name="wp8cyclesmallkey" value=""/>
    <attributes name="win8versionrevisionkey" value="0"/>
    <attributes name="ACCESS_LOCATION_EXTRA_COMMANDS" value="false"/>
    <attributes name="hybridportkey" value=""/>
    <attributes name="andmanifesttags" value=""/>
    <attributes name="ACCESS_MOCK_LOCATION" value="false"/>
    <attributes name="SYSTEM_ALERT_WINDOW" value="false"/>
    <attributes name="WRITE_CONTACTS" value="false"/>
    <attributes name="VIBRATE" value="false"/>
    <attributes name="iphoneloadindicatorkey" value="true"/>
    <attributes name="ID_CAP_IDENTITY_DEVICE" value="true"/>
    <attributes name="RECEIVE_SMS" value="false"/>
    <attributes name="BIND_REMOTEVIEWS" value="false"/>
    <attributes name="appidkey" value="helloworld"/>
    <attributes name="win8smalllogokey" value=""/>
    <attributes name="SET_DEBUG_APP" value="false"/>
    <attributes name="tcandroid240basefontsize" value="10"/>
    <attributes name="Proximity" value="true"/>
    <attributes name="win8versionbuildkey" value="0"/>
    <attributes name="CHANGE_COMPONENT_ENABLED_STATE" value="false"/>
    <attributes name="DELETE_CACHE_FILES" value="false"/>
    <attributes name="bbserviceidentifierpattern" value=""/>
    <attributes name="BATTERY_STATS" value="false"/>
    <attributes name="supportmarginpixelindip" value="true"/>
    <attributes name="win8toastcapablekey" value="no"/>
    <attributes name="iphonewebshrtcutkey" value=""/>
    <attributes name="ID_CAP_NETWORKING" value="true"/>
    <attributes name="ACCESS_CHECKIN_PROPERTIES" value="false"/>
    <attributes name="Webcam" value="true"/>
    <attributes name="ID_HW_FRONTCAMERA" value="false"/>
    <attributes name="winmobileguidkey" value="e043bf2a-5236-4e49-827b-b380a74b5430"/>
    <attributes name="tcbjs240basefontsize" value="10"/>
    <attributes name="desktopstartupformkey" value="frmHome"/>
    <attributes name="SET_ALWAYS_FINISH" value="false"/>
    <attributes name="apptitle" value=""/>
    <attributes name="apppackagekey" value="com.orgname.hw"/>
    <attributes name="SET_ALARM" value="false"/>
    <attributes name="ID_CAP_MAP" value="true"/>
    <attributes name="ID_REQ_NFC" value="false"/>
    <attributes name="androidorientation" value="Both"/>
    <attributes name="RECEIVE_MMS" value="false"/>
    <attributes name="WRITE_SYNC_SETTINGS" value="false"/>
    <attributes name="tcbb440basefontsize" value="15"/>
    <attributes name="WRITE_EXTERNAL_STORAGE" value="false"/>
    <attributes name="win8descriptionkey" value="Sample Test Application"/>
    <attributes name="iphoneurlscheme" value=""/>
    <attributes name="REORDER_TASKS" value="false"/>
    <attributes name="STATUS_BAR" value="false"/>
    <attributes name="iphonebundleidentifierkey" value="com.kony.HelloWorld"/>
    <attributes name="spaandroidtabbasefontsize" value="17"/>
    <attributes name="SET_WALLPAPER" value="false"/>
    <attributes name="ID_REQ_MAGNETOMETER" value="false"/>
    <attributes name="Microphone" value="true"/>
    <attributes name="ID_CAP_SENSORS" value="true"/>
    <attributes name="READ_SYNC_STATS" value="false"/>
    <attributes name="EXPAND_STATUS_BAR" value="false"/>
    <attributes name="SEND_SMS" value="false"/>
    <attributes name="desktopwebfavico" value=""/>
    <attributes name="androidscreennormal" value="true"/>
    <attributes name="WAKE_LOCK" value="false"/>
    <attributes name="wp8iconicmediumkey" value=""/>
    <attributes name="SET_ACTIVITY_WATCHER" value="false"/>
    <attributes name="tcnth320basefontsize" value="15"/>
    <attributes name="project.type" value="js"/>
    <attributes name="tcxhtmlbasefontsize" value="10"/>
    <attributes name="ID_CAP_CONTACTS" value="true"/>
    <attributes name="defaultlocalekey" value=""/>
    <attributes name="WRITE_APN_SETTINGS" value="false"/>
    <attributes name="ID_CAP_PUSH_NOTIFICATION" value="true"/>
    <attributes name="CONTROL_LOCATION_UPDATES" value="false"/>
    <attributes name="ID_CAP_CAMERA" value="false"/>
    <attributes name="win8shortnamekey" value="HelloWorld"/>
    <attributes name="MASTER_CLEAR" value="false"/>
    <attributes name="SIGNAL_PERSISTENT_PROCESSES" value="false"/>
    <attributes name="tcnoscriptmessage" value="To use this site, first enable your browser&#039;s JavaScript support and then refresh this page."/>
    <attributes name="tcbb240basefontsize" value="12"/>
    <attributes name="wp8supportlargetileskey" value="true"/>
    <attributes name="wp8displaynamekey" value="HelloWorld"/>
    <attributes name="win8shownamekey" value="Not set"/>
    <attributes name="androidscreensmall" value="true"/>
    <attributes name="Documents_Library_Access" value="false"/>
    <attributes name="wp8cycle9key" value=""/>
    <attributes name="MOUNT_UNMOUNT_FILESYSTEMS" value="false"/>
    <attributes name="winmobiletileimagekey" value=""/>
    <attributes name="BROADCAST_WAP_PUSH" value="false"/>
    <attributes name="tcandroid480basefontsize" value="16"/>
    <attributes name="BROADCAST_SMS" value="false"/>
    <attributes name="tcandroid320basefontsize" value="12"/>
    <attributes name="FACTORY_TEST" value="false"/>
    <attributes name="win8publisherdisplaynamekey" value="KonyLabs"/>
    <attributes name="tcphoneformatindicator" value="false"/>
    <attributes name="ID_REQ_REARCAMERA" value="false"/>
    <attributes name="Location" value="true"/>
    <attributes name="tcandroid360basefontsize" value="13"/>
    <attributes name="win8displaynamekey" value="HelloWorld"/>
    <attributes name="wp8cycle7key" value=""/>
    <attributes name="tcbb400basefontsize" value="14"/>
    <attributes name="bbservicemenuitemlabel" value=""/>
    <attributes name="ACCESS_SURFACE_FLINGER" value="false"/>
    <attributes name="ID_CAP_WEBBROWSERCOMPONENT" value="true"/>
    <attributes name="mwhttpsportkey" value="443"/>
    <attributes name="pathkey" value=""/>
    <attributes name="FORCE_BACK" value="false"/>
    <attributes name="vendornamekey" value="KonyLabs"/>
    <attributes name="fgcolorkey" value="255,255,255"/>
    <attributes name="APPLICATION_THEME" value="default"/>
    <attributes name="mapkey" value=""/>
    <attributes name="win8applogokey" value=""/>
    <attributes name="camerasettings" value=""/>
    <attributes name="pathprefixkey" value=""/>
    <attributes name="defaultlocalekey" value=""/>
</properties>